fstotv.py
devices/__init__.py
devices/chromecast.py
fstotv/__init__.py
fstotv/devices/__init__.py
fstotv/devices/chromecast.py
fstotv-1.0.3.dist-info/METADATA
fstotv-1.0.3.dist-info/WHEEL
fstotv-1.0.3.dist-info/entry_points.txt
fstotv-1.0.3.dist-info/top_level.txt
fstotv-1.0.3.dist-info/RECORD
