Metadata-Version: 2.1
Name: fstotv
Version: 1.0.3
Summary: send video in local to chromecast
Home-page: https://github.com/agalera/fstotv
Author: Alberto Galera Jimenez
Author-email: galerajimenez@gmail.com
License: UNKNOWN
Platform: UNKNOWN
Requires-Dist: bottle
Requires-Dist: pychromecast
